copy_spotlights/__init__.py
copy_spotlights/command_line.py
copy_spotlights/copy_spotlights.py
copy_spotlights/gui.py
get_spotlights-3.2.dist-info/LICENSE
get_spotlights-3.2.dist-info/METADATA
get_spotlights-3.2.dist-info/WHEEL
get_spotlights-3.2.dist-info/entry_points.txt
get_spotlights-3.2.dist-info/top_level.txt
get_spotlights-3.2.dist-info/RECORD
