Metadata-Version: 2.1
Name: get-spotlights
Version: 3.2
Summary: Love windows 10 spotlight images that show up on lock-screen. Then here's a simple program to copy those images and get them in your preferred directory.
Home-page: https://github.com/ksharshveer/copy-windows10-spotlight-images
Author: Harshveer Singh
Author-email: ksharshveer@gmail.com
License: MIT
Keywords: copy extract get windows 10 spotlight spotlights image images lockscreen wallpaper
License-File: LICENSE
Requires-Dist: pillow
